pygrams/generators.py
pygrams/getters.py
pygrams/has_elements.py
pygrams/is_elements.py
pygrams/others.py
pygrams/pygrams.py
pygrams/searching.py
pygrams/sorting.py
pygrams/data_manipulation/data_processing.py
pygrams/data_manipulation/data_viz.py
pygrams/utils/algorithmic_utils.py
pygrams/utils/array_utils.py
pygrams/utils/date_and_time_utils.py
pygrams/utils/default_utils.py
pygrams/utils/file_utils.py
pygrams/utils/geolocation_utils.py
pygrams/utils/math_utils.py
pygrams/utils/network_utils.py
pygrams/utils/string_utils.py
pygrams/utils/unit_utils.py
pygrams-0.0.27.dist-info/LICENSE
pygrams-0.0.27.dist-info/METADATA
pygrams-0.0.27.dist-info/WHEEL
pygrams-0.0.27.dist-info/top_level.txt
pygrams-0.0.27.dist-info/RECORD
