Metadata-Version: 2.1
Name: pygrams
Version: 0.0.27
Summary: Get python programs handy as a function
Home-page: https://pygrams.netlify.app
Download-URL: https://github.com/Yaseen549/pygrams/archive/refs/tags/v0.0.27.tar.gz
Author: Yaseen
Author-email: fantasticyaseenshariff@gmail.com
License: MIT
Keywords: PYTHONPROGRAMS,PROGRAMS,FUNCTIONS,PYGRAMS
Classifier: Development Status :: 3 - Alpha
Classifier: Intended Audience :: Developers
Classifier: Topic :: Software Development :: Build Tools
Classifier: License :: OSI Approved :: MIT License
Classifier: Programming Language :: Python :: 3
Classifier: Programming Language :: Python :: 3.4
Classifier: Programming Language :: Python :: 3.5
Classifier: Programming Language :: Python :: 3.6
License-File: LICENSE
